{
  "project_info": {
    "project_number": "42290391696",
    "firebase_url": "https://cis3334-part12-firebase-auth-s.firebaseio.com",
    "project_id": "cis3334-part12-firebase-auth-s",
    "storage_bucket": "cis3334-part12-firebase-auth-s.appspot.com"
  },
  "client": [
    {
      "client_info": {
        "mobilesdk_app_id": "1:42290391696:android:8a263ec549856a8a",
        "android_client_info": {
          "package_name": "css.cis3334.firebaseauthentication"
        }
      },
      "oauth_client": [
        {
          "client_id": "42290391696-s07rni4hj8nfjv25io3iv3e1a95sqh1q.apps.googleusercontent.com",
          "client_type": 1,
          "android_info": {
            "package_name": "css.cis3334.firebaseauthentication",
            "certificate_hash": "6cace2c6d79ebe0f0be05f189537d26a13beac3e"
          }
        },
        {
          "client_id": "42290391696-kk21tt42mitsdd1u5lcralqj8hdvqfug.apps.googleusercontent.com",
          "client_type": 3
        }
      ],
      "api_key": [
        {
          "current_key": "AIzaSyDjNdgzQlk8xEHi0lnV3T7huH-iIEBXoow"
        }
      ],
      "services": {
        "analytics_service": {
          "status": 1
        },
        "appinvite_service": {
          "status": 2,
          "other_platform_oauth_client": [
            {
              "client_id": "42290391696-kk21tt42mitsdd1u5lcralqj8hdvqfug.apps.googleusercontent.com",
              "client_type": 3
            }
          ]
        },
        "ads_service": {
          "status": 2
        }
      }
    }
  ],
  "configuration_version": "1"
}